AnimationDonghuaXiangjie/README.md
AnimationDonghuaXiangjie/__init__.py
AnimationDonghuaXiangjie/__main__.py
AnimationDonghuaXiangjie/file.epub
AnimationDonghuaXiangjie/index.html
AnimationDonghuaXiangjie/css/__init__.py
AnimationDonghuaXiangjie/css/annotations.css
AnimationDonghuaXiangjie/css/main.css
AnimationDonghuaXiangjie/css/normalize.css
AnimationDonghuaXiangjie/css/popup.css
AnimationDonghuaXiangjie/font/__init__.py
AnimationDonghuaXiangjie/font/fontello.eot
AnimationDonghuaXiangjie/font/fontello.svg
AnimationDonghuaXiangjie/font/fontello.ttf
AnimationDonghuaXiangjie/font/fontello.woff
AnimationDonghuaXiangjie/img/__init__.py
AnimationDonghuaXiangjie/img/annotator-glyph-sprite.png
AnimationDonghuaXiangjie/img/annotator-icon-sprite.png
AnimationDonghuaXiangjie/img/apple-touch-icon.png
AnimationDonghuaXiangjie/img/cancelfullscreen.png
AnimationDonghuaXiangjie/img/close.png
AnimationDonghuaXiangjie/img/fullscreen.png
AnimationDonghuaXiangjie/img/loader.gif
AnimationDonghuaXiangjie/img/menu-icon.png
AnimationDonghuaXiangjie/img/save.png
AnimationDonghuaXiangjie/img/saved.png
AnimationDonghuaXiangjie/img/settings-s.png
AnimationDonghuaXiangjie/img/settings.png
AnimationDonghuaXiangjie/img/star.png
AnimationDonghuaXiangjie/js/__init__.py
AnimationDonghuaXiangjie/js/epub.js
AnimationDonghuaXiangjie/js/epub.min.js
AnimationDonghuaXiangjie/js/epub.min.map
AnimationDonghuaXiangjie/js/hooks.min.js
AnimationDonghuaXiangjie/js/hooks.min.map
AnimationDonghuaXiangjie/js/reader.js
AnimationDonghuaXiangjie/js/reader.js.map
AnimationDonghuaXiangjie/js/reader.min.js
AnimationDonghuaXiangjie/js/reader.min.map
AnimationDonghuaXiangjie/js/hooks/__init__.py
AnimationDonghuaXiangjie/js/hooks/extensions/__init__.py
AnimationDonghuaXiangjie/js/hooks/extensions/highlight.js
AnimationDonghuaXiangjie/js/libs/__init__.py
AnimationDonghuaXiangjie/js/libs/jquery.min.js
AnimationDonghuaXiangjie/js/libs/localforage.min.js
AnimationDonghuaXiangjie/js/libs/screenfull.js
animation_donghua_xiangjie-2024.3.3.0.dist-info/METADATA
animation_donghua_xiangjie-2024.3.3.0.dist-info/WHEEL
animation_donghua_xiangjie-2024.3.3.0.dist-info/entry_points.txt
animation_donghua_xiangjie-2024.3.3.0.dist-info/top_level.txt
animation_donghua_xiangjie-2024.3.3.0.dist-info/RECORD
